patas/__init__.py
patas/argparsers.py
patas/consts.py
patas/graphics.old.py
patas/graphics.py
patas/grid_exec.py
patas/grid_explorer.py
patas/log.py
patas/main.py
patas/parse.py
patas/query.py
patas/query_engine.py
patas/scheduler.py
patas/schemas.py
patas/utils.py
tests/__init__.py
tests/test_schemas.py
patas-2.0.6.dist-info/METADATA
patas-2.0.6.dist-info/WHEEL
patas-2.0.6.dist-info/entry_points.txt
patas-2.0.6.dist-info/top_level.txt
patas-2.0.6.dist-info/RECORD
