Metadata-Version: 2.1
Name: patas
Version: 2.0.6
Summary: Hyperparameter search with a single command
Home-page: https://github.com/diegofps/patas
Author: Diego Souza
Author-email: diegofpsouza+patas@gmail.com
Classifier: Programming Language :: Python :: 3
Classifier: License :: OSI Approved :: MIT License
Classifier: Operating System :: OS Independent
Requires-Dist: csvkit
Requires-Dist: seaborn
Provides-Extra: full
